<?xml version="1.0"?>
<regress-exe>

<test>
   <default>
      <files>crypto.js</files>
      <baseline />
   </default>
</test>

<test>
   <default>
      <files>deltablue.js</files>
      <baseline />
   </default>
</test>

<test>
   <default>
      <files>earley-boyer.js</files>
      <baseline />
   </default>
</test>

<test>
   <default>
      <files>raytrace.js</files>
      <baseline />
   </default>
</test>

<test>
   <default>
      <files>regexp.js</files>
      <baseline />
   </default>
</test>

<test>
   <default>
      <files>richards.js</files>
      <baseline />
   </default>
</test>

<test>
   <default>
      <files>splay.js</files>
      <baseline />
   </default>
</test>

</regress-exe>
