<?xml version="1.0" encoding="utf-8"?>
<regress-exe>
<dir>
  <default>
    <files>msrc</files>
  </default>
</dir>
<dir>
  <default>
    <files>InlineCaches</files>
  </default>
</dir>
<dir>
  <default>
    <files>jd</files>
    <tags>exclude_serialized</tags>
  </default>
</dir>
<dir>
  <default>
    <files>NativeUnitTests</files>
  </default>
</dir>
<dir>
  <default>
    <files>SunSpider</files>
    <tags>exclude_snap,Slow</tags>
  </default>
</dir>
<dir>
  <default>
    <files>SunSpider1.0.2</files>
    <tags>exclude_snap,Slow</tags>
  </default>
</dir>
<dir>
  <default>
    <files>SunSpiderFunctionality</files>
    <tags>exclude_snap,Slow</tags>
  </default>
</dir>
<dir>
  <default>
    <files>V8</files>
    <tags>exclude_snap,Slow</tags>
  </default>
</dir>
<dir>
  <default>
    <files>V8_Functionality</files>
    <tags>exclude_snap,Slow</tags>
  </default>
</dir>
<dir>
  <default>
    <files>Basics</files>
  </default>
</dir>
<dir>
  <default>
    <files>Strings</files>
  </default>
</dir>
<dir>
  <default>
    <files>Date</files>
  </default>
</dir>
<dir>
  <default>
    <files>Error</files>
  </default>
</dir>
<dir>
  <default>
    <files>Math</files>
  </default>
</dir>
<dir>
  <default>
    <files>Array</files>
  </default>
</dir>
<dir>
  <default>
    <files>Optimizer</files>
  </default>
</dir>
<dir>
  <default>
    <files>Function</files>
  </default>
</dir>
<dir>
  <default>
    <files>Object</files>
  </default>
</dir>
<dir>
  <default>
    <files>Operators</files>
  </default>
</dir>
<dir>
  <default>
    <files>Lib</files>
  </default>
</dir>
<dir>
  <default>
    <files>JSON</files>
  </default>
</dir>
<dir>
  <default>
    <files>Intl</files>
  </default>
</dir>
<dir>
  <default>
    <files>IntlCore</files>
  </default>
</dir>
<dir>
  <default>
    <files>Debugger</files>
    <tags>exclude_serialized</tags>
  </default>
</dir>
<dir>
  <default>
    <files>DebuggerCommon</files>
    <tags>exclude_serialized</tags>
    <sourcepath>..\core\test\DebuggerCommon</sourcepath>
  </default>
</dir>
<dir>
  <default>
    <files>Bugs</files>
  </default>
</dir>
<dir>
  <default>
    <files>strict</files>
  </default>
</dir>
<dir>
  <default>
    <files>typedarray</files>
  </default>
</dir>
<dir>
  <default>
    <files>sca</files>
  </default>
</dir>
<dir>
  <default>
    <files>crossthread</files>
  </default>
</dir>
<dir>
  <default>
    <files>Loop</files>
  </default>
</dir>
<dir>
  <default>
    <files>StackTrace</files>
  </default>
</dir>
<dir>
  <default>
    <files>Miscellaneous</files>
  </default>
</dir>
<dir>
  <default>
    <files>fieldopts</files>
  </default>
</dir>
<dir>
  <default>
    <files>FixedFields</files>
  </default>
</dir>
<dir>
  <default>
    <files>HeapEnum</files>
  </default>
</dir>
<dir>
  <default>
    <files>InternalProfile</files>
  </default>
</dir>
<dir>
  <default>
    <files>es6</files>
  </default>
</dir>
<dir>
  <default>
    <files>AsyncDebug</files>
    <tags>exclude_serialized</tags>
  </default>
</dir>
<dir>
  <default>
    <files>Profiler</files>
  </default>
</dir>
<dir>
  <default>
    <files>host</files>
  </default>
</dir>
<dir>
  <default>
    <files>iasd</files>
  </default>
</dir>
<dir>
  <default>
    <files>KrakenFunctionality</files>
  </default>
</dir>
<dir>
  <default>
    <files>AsmJs</files>
    <tags>exclude_apollo,exclude_dynapogo,exclude_serialized,exclude_arm,exclude_arm64</tags>
  </default>
</dir>
<dir>
  <default>
    <files>bailout</files>
  </default>
</dir>
<dir>
  <default>
    <files>Regex</files>
  </default>
</dir>
<dir>
  <default>
    <files>UnifiedRegex</files>
  </default>
</dir>
<dir>
  <default>
    <files>utf8</files>
  </default>
</dir>
</regress-exe>
